README.rst
setup.py
multiprocessing_on_dill/__init__.py
multiprocessing_on_dill/connection.py
multiprocessing_on_dill/context.py
multiprocessing_on_dill/forkserver.py
multiprocessing_on_dill/heap.py
multiprocessing_on_dill/managers.py
multiprocessing_on_dill/pool.py
multiprocessing_on_dill/popen_fork.py
multiprocessing_on_dill/popen_forkserver.py
multiprocessing_on_dill/popen_spawn_posix.py
multiprocessing_on_dill/popen_spawn_win32.py
multiprocessing_on_dill/process.py
multiprocessing_on_dill/queues.py
multiprocessing_on_dill/reduction.py
multiprocessing_on_dill/resource_sharer.py
multiprocessing_on_dill/semaphore_tracker.py
multiprocessing_on_dill/sharedctypes.py
multiprocessing_on_dill/spawn.py
multiprocessing_on_dill/synchronize.py
multiprocessing_on_dill/util.py
multiprocessing_on_dill.egg-info/PKG-INFO
multiprocessing_on_dill.egg-info/SOURCES.txt
multiprocessing_on_dill.egg-info/dependency_links.txt
multiprocessing_on_dill.egg-info/entry_points.txt
multiprocessing_on_dill.egg-info/requires.txt
multiprocessing_on_dill.egg-info/top_level.txt
multiprocessing_on_dill/dummy/__init__.py
multiprocessing_on_dill/dummy/connection.py
test/test_lambda.py