Metadata-Version: 1.1
Name: multiprocessing-on-dill
Version: 3.5.0a4
Summary: A friendly fork of multiprocessing which uses dill instead of pickle
Home-page: https://github.com/sixty-north/multiprocessing_on_dill
Author: Robert Smallshire
Author-email: rob@sixty-north.com
License: PSFL
Keywords: multiprocessing parallel
Platform: UNKNOWN
Classifier: Development Status :: 5 - Production/Stable
Classifier: Intended Audience :: Developers
Classifier: Topic :: Software Development :: Libraries :: Python Modules
Classifier: License :: OSI Approved :: Python Software Foundation License
Classifier: Programming Language :: Python :: 3 :: Only
